{
    "id": "ansible-galaxy",
    "version": "0.0.1",
    "name": "Ansible galaxy collections",
    "documentationURL": "https://github.com/framctr/devcontainer-features/tree/main/src/ansible-galaxy",
    "description": "Install ansible galaxy collections.",
    "options": {
        "collections": {
            "type": "string",
            "default": "",
            "description": "Install collections (space separated)"
        }
    },
    "installsAfter": [
        "ghcr.io/devcontainers-contrib/features/ansible"
    ]
}